{
    "appKeys": {
        "KEY_DEBT": 0,
        "KEY_IS_GREEN": 1
    },
    "capabilities": [
        ""
    ],
    "companyName": "nickmsoccer@gmail.com",
    "enableMultiJS": true,
    "longName": "Debt Clock",
    "projectType": "native",
    "resources": {
        "media": []
    },
    "sdkVersion": "3",
    "shortName": "Debt Clock",
    "targetPlatforms": [
        "aplite",
        "basalt",
        "chalk"
    ],
    "uuid": "034fbbe6-0f68-419b-9a42-f1cc7fb85156",
    "versionLabel": "1.0",
    "watchapp": {
        "watchface": false
    }
}
